{
    "S. Abid": {
        "listOfRef": [
            "1"
        ],
        "first": "S",
        "last": "Abid",
        "id": 1
    },
    "G. Dupre": {
        "listOfRef": [
            "1",
            "97"
        ],
        "first": "G",
        "last": "Dupre",
        "id": 2
    },
    "C. Paillard": {
        "listOfRef": [
            "1",
            "96"
        ],
        "first": "C",
        "last": "Paillard",
        "id": 3
    },
    "G.L. Agafonov": {
        "listOfRef": [
            "2"
        ],
        "first": "G",
        "middle": "L",
        "last": "Agafonov",
        "id": 4
    },
    "S.M. Frolov": {
        "listOfRef": [
            "2"
        ],
        "first": "S",
        "middle": "M",
        "last": "Frolov",
        "id": 5
    },
    "R. Akbar": {
        "listOfRef": [
            "3"
        ],
        "first": "R",
        "last": "Akbar",
        "id": 6
    },
    "M.J. Kaneshige": {
        "listOfRef": [
            "3",
            "53"
        ],
        "first": "M",
        "middle": "J",
        "last": "Kaneshige",
        "id": 7
    },
    "E. Schultz": {
        "listOfRef": [
            "3",
            "98"
        ],
        "first": "E",
        "last": "Schultz",
        "id": 8
    },
    "J.E. Shepherd": {
        "listOfRef": [
            "3",
            "57",
            "97",
            "98",
            "99",
            "103",
            "104",
            "113"
        ],
        "first": "J",
        "middle": "E",
        "last": "Shepherd",
        "id": 9
    },
    "M. Aminallah": {
        "listOfRef": [
            "4"
        ],
        "first": "M",
        "last": "Aminallah",
        "id": 10
    },
    "J. Brossard": {
        "listOfRef": [
            "4"
        ],
        "first": "J",
        "last": "Brossard",
        "id": 11
    },
    "A. Vasiliev": {
        "listOfRef": [
            "4"
        ],
        "first": "A",
        "last": "Vasiliev",
        "id": 12
    },
    "T.J. Anderson": {
        "listOfRef": [
            "5"
        ],
        "first": "T",
        "middle": "J",
        "last": "Anderson",
        "id": 13
    },
    "E.K. Dabora": {
        "listOfRef": [
            "5"
        ],
        "first": "E",
        "middle": "K",
        "last": "Dabora",
        "id": 14
    },
    "P. Andresen": {
        "listOfRef": [
            "6"
        ],
        "first": "P",
        "last": "Andresen",
        "id": 15
    },
    "W. Reckers": {
        "listOfRef": [
            "6"
        ],
        "first": "W",
        "last": "Reckers",
        "id": 16
    },
    "R. Atkinson": {
        "listOfRef": [
            "7"
        ],
        "first": "R",
        "last": "Atkinson",
        "id": 17
    },
    "D.C. Bull": {
        "listOfRef": [
            "7",
            "21",
            "22",
            "23",
            "24",
            "25",
            "26",
            "27"
        ],
        "first": "D",
        "middle": "C",
        "last": "Bull",
        "id": 18
    },
    "P.J. Shuff": {
        "listOfRef": [
            "7",
            "27",
            "44",
            "116"
        ],
        "first": "P",
        "middle": "J",
        "last": "Shuff",
        "id": 19
    },
    "G.G. Bach": {
        "listOfRef": [
            "8"
        ],
        "first": "G",
        "middle": "G",
        "last": "Bach",
        "id": 20
    },
    "R. Knystautas": {
        "listOfRef": [
            "8",
            "14",
            "16",
            "48",
            "49",
            "54",
            "55",
            "56",
            "57",
            "62",
            "66",
            "67",
            "70",
            "74",
            "77",
            "83",
            "85",
            "87",
            "97",
            "113"
        ],
        "first": "R",
        "last": "Knystautas",
        "id": 21
    },
    "J.H. Lee": {
        "listOfRef": [
            "8",
            "14",
            "49",
            "54",
            "55",
            "56",
            "63",
            "64",
            "65",
            "66",
            "67",
            "68",
            "69",
            "74",
            "83",
            "85",
            "87",
            "88",
            "89",
            "90",
            "91",
            "97"
        ],
        "first": "J",
        "middle": "H",
        "last": "Lee",
        "id": 22
    },
    "H.O. Barthel": {
        "listOfRef": [
            "9"
        ],
        "first": "H",
        "middle": "O",
        "last": "Barthel",
        "id": 23
    },
    "P. Bauer": {
        "listOfRef": [
            "10",
            "11",
            "12"
        ],
        "first": "P",
        "last": "Bauer",
        "id": 24
    },
    "C. Brochet": {
        "listOfRef": [
            "11",
            "12"
        ],
        "first": "C",
        "last": "Brochet",
        "id": 25
    },
    "H.N. Presles": {
        "listOfRef": [
            "11",
            "12",
            "37"
        ],
        "first": "H",
        "middle": "N",
        "last": "Presles",
        "id": 26
    },
    "O. Heuze": {
        "listOfRef": [
            "12"
        ],
        "first": "O",
        "last": "Heuze",
        "id": 27
    },
    "H.D. Beeson": {
        "listOfRef": [
            "13"
        ],
        "first": "H",
        "middle": "D",
        "last": "Beeson",
        "id": 28
    },
    "R.D. McClenagan": {
        "listOfRef": [
            "13",
            "97",
            "99"
        ],
        "first": "R",
        "middle": "D",
        "last": "McClenagan",
        "id": 29
    },
    "C.V. Bishop": {
        "listOfRef": [
            "13",
            "97"
        ],
        "first": "C",
        "middle": "V",
        "last": "Bishop",
        "id": 30
    },
    "F.J. Benz": {
        "listOfRef": [
            "13",
            "97",
            "99"
        ],
        "first": "F",
        "middle": "J",
        "last": "Benz",
        "id": 31
    },
    "W.J. Pitz": {
        "listOfRef": [
            "13",
            "114",
            "126"
        ],
        "first": "W",
        "middle": "J",
        "last": "Pitz",
        "id": 32
    },
    "C.K. Westbrook": {
        "listOfRef": [
            "13",
            "87",
            "114",
            "126",
            "127"
        ],
        "first": "C",
        "middle": "K",
        "last": "Westbrook",
        "id": 33
    },
    "J.H.S. Lee": {
        "listOfRef": [
            "13",
            "16",
            "48",
            "57",
            "62",
            "70",
            "77",
            "99",
            "113"
        ],
        "first": "J",
        "middle": "H.S",
        "last": "Lee",
        "id": 34
    },
    "W.B. Benedick": {
        "listOfRef": [
            "14",
            "15",
            "16",
            "48",
            "105",
            "112",
            "113"
        ],
        "first": "W",
        "middle": "B",
        "last": "Benedick",
        "id": 35
    },
    "C.M. Guirao": {
        "listOfRef": [
            "14",
            "48",
            "49",
            "54",
            "56",
            "70"
        ],
        "first": "C",
        "middle": "M",
        "last": "Guirao",
        "id": 36
    },
    "J.D. Kennedy": {
        "listOfRef": [
            "15"
        ],
        "first": "J",
        "middle": "D",
        "last": "Kennedy",
        "id": 37
    },
    "B. Morosin": {
        "listOfRef": [
            "15"
        ],
        "first": "B",
        "last": "Morosin",
        "id": 38
    },
    "A.A. Borisov": {
        "listOfRef": [
            "17",
            "18",
            "19",
            "20"
        ],
        "first": "A",
        "middle": "A",
        "last": "Borisov",
        "id": 39
    },
    "S.V. Khomic": {
        "listOfRef": [
            "17"
        ],
        "first": "S",
        "middle": "V",
        "last": "Khomic",
        "id": 40
    },
    "V.N. Mikhalkin": {
        "listOfRef": [
            "17",
            "18",
            "19"
        ],
        "first": "V",
        "middle": "N",
        "last": "Mikhalkin",
        "id": 41
    },
    "S.V. Khomik": {
        "listOfRef": [
            "18",
            "19"
        ],
        "first": "S",
        "middle": "V",
        "last": "Khomik",
        "id": 42
    },
    "E.V. Saneev": {
        "listOfRef": [
            "18"
        ],
        "first": "E",
        "middle": "V",
        "last": "Saneev",
        "id": 43
    },
    "V.V. Kosenkov": {
        "listOfRef": [
            "19"
        ],
        "first": "V",
        "middle": "V",
        "last": "Kosenkov",
        "id": 44
    },
    "A.E. Mailkov": {
        "listOfRef": [
            "19"
        ],
        "first": "A",
        "middle": "E",
        "last": "Mailkov",
        "id": 45
    },
    "S. Loban'": {
        "listOfRef": [
            "20"
        ],
        "first": "S",
        "last": "Loban'",
        "id": 46
    },
    "J.E. Elsworth": {
        "listOfRef": [
            "23",
            "24",
            "25",
            "26",
            "27",
            "43",
            "44"
        ],
        "first": "J",
        "middle": "E",
        "last": "Elsworth",
        "id": 47
    },
    "G. Hooper": {
        "listOfRef": [
            "23",
            "24",
            "25",
            "26",
            "41",
            "42"
        ],
        "first": "G",
        "last": "Hooper",
        "id": 48
    },
    "C.P. Quinn": {
        "listOfRef": [
            "26"
        ],
        "first": "C",
        "middle": "P",
        "last": "Quinn",
        "id": 49
    },
    "E. Metcalfe": {
        "listOfRef": [
            "27"
        ],
        "first": "E",
        "last": "Metcalfe",
        "id": 50
    },
    "G.A. Carlson": {
        "listOfRef": [
            "28"
        ],
        "first": "G",
        "middle": "A",
        "last": "Carlson",
        "id": 51
    },
    "G. Ciccarelli": {
        "listOfRef": [
            "29",
            "30"
        ],
        "first": "G",
        "last": "Ciccarelli",
        "id": 52
    },
    "T. Ginsberg": {
        "listOfRef": [
            "29",
            "30"
        ],
        "first": "T",
        "last": "Ginsberg",
        "id": 53
    },
    "J. Boccio": {
        "listOfRef": [
            "29",
            "30"
        ],
        "first": "J",
        "last": "Boccio",
        "id": 54
    },
    "C. Economos": {
        "listOfRef": [
            "29"
        ],
        "first": "C",
        "last": "Economos",
        "id": 55
    },
    "K. Sato": {
        "listOfRef": [
            "29"
        ],
        "first": "K",
        "last": "Sato",
        "id": 56
    },
    "M. Kinoshita": {
        "listOfRef": [
            "29"
        ],
        "first": "M",
        "last": "Kinoshita",
        "id": 57
    },
    "C. Finfrock": {
        "listOfRef": [
            "30"
        ],
        "first": "C",
        "last": "Finfrock",
        "id": 58
    },
    "L. Gerlach": {
        "listOfRef": [
            "30"
        ],
        "first": "L",
        "last": "Gerlach",
        "id": 59
    },
    "H. Tagawa": {
        "listOfRef": [
            "30"
        ],
        "first": "H",
        "last": "Tagawa",
        "id": 60
    },
    "A. Malliakos": {
        "listOfRef": [
            "30"
        ],
        "first": "A",
        "last": "Malliakos",
        "id": 61
    },
    "Yu.N. Denisov": {
        "listOfRef": [
            "31",
            "32"
        ],
        "first": "Yu",
        "middle": "N",
        "last": "Denisov",
        "id": 62
    },
    "Ya.K. Troshin": {
        "listOfRef": [
            "31",
            "32"
        ],
        "first": "Ya",
        "middle": "K",
        "last": "Troshin",
        "id": 63
    },
    "D. Desbordes": {
        "listOfRef": [
            "33",
            "34",
            "35",
            "36",
            "37",
            "38",
            "130"
        ],
        "first": "D",
        "last": "Desbordes",
        "id": 64
    },
    "C. Guerraud": {
        "listOfRef": [
            "37",
            "130"
        ],
        "first": "C",
        "last": "Guerraud",
        "id": 65
    },
    "L. Hamada": {
        "listOfRef": [
            "37"
        ],
        "first": "L",
        "last": "Hamada",
        "id": 66
    },
    "M. Vachon": {
        "listOfRef": [
            "38"
        ],
        "first": "M",
        "last": "Vachon",
        "id": 67
    },
    "EDL": {
        "listOfRef": [
            "39"
        ],
        "last": "EDL",
        "id": 68
    },
    "D.H. Edwards": {
        "listOfRef": [
            "40",
            "41",
            "42"
        ],
        "first": "D",
        "middle": "H",
        "last": "Edwards",
        "id": 69
    },
    "J.M. Morgan": {
        "listOfRef": [
            "41",
            "42"
        ],
        "first": "J",
        "middle": "M",
        "last": "Morgan",
        "id": 70
    },
    "G.O. Thomas": {
        "listOfRef": [
            "42"
        ],
        "first": "G",
        "middle": "O",
        "last": "Thomas",
        "id": 71
    },
    "J.A. Eyre": {
        "listOfRef": [
            "43",
            "116"
        ],
        "first": "J",
        "middle": "A",
        "last": "Eyre",
        "id": 72
    },
    "Aziz Ungut": {
        "listOfRef": [
            "44",
            "116"
        ],
        "first": "Aziz",
        "last": "Ungut",
        "id": 73
    },
    "H. Freiwald": {
        "listOfRef": [
            "45"
        ],
        "first": "H",
        "last": "Freiwald",
        "id": 74
    },
    "H.W. Koch": {
        "listOfRef": [
            "45"
        ],
        "first": "H",
        "middle": "W",
        "last": "Koch",
        "id": 75
    },
    "R.S. Fry": {
        "listOfRef": [
            "46"
        ],
        "first": "R",
        "middle": "S",
        "last": "Fry",
        "id": 76
    },
    "J.A. Nicholls": {
        "listOfRef": [
            "46",
            "92",
            "118",
            "128"
        ],
        "first": "J",
        "middle": "A",
        "last": "Nicholls",
        "id": 77
    },
    "K. Guhlmann": {
        "listOfRef": [
            "47"
        ],
        "first": "K",
        "last": "Guhlmann",
        "id": 78
    },
    "W. Pusch": {
        "listOfRef": [
            "47",
            "100",
            "101"
        ],
        "first": "W",
        "last": "Pusch",
        "id": 79
    },
    "H.G. Wagner": {
        "listOfRef": [
            "47",
            "100",
            "101"
        ],
        "first": "H",
        "middle": "G",
        "last": "Wagner",
        "id": 80
    },
    "M. Berman": {
        "listOfRef": [
            "48",
            "112"
        ],
        "first": "M",
        "last": "Berman",
        "id": 81
    },
    "T. Hikita": {
        "listOfRef": [
            "50"
        ],
        "first": "T",
        "last": "Hikita",
        "id": 82
    },
    "al. et": {
        "listOfRef": [
            "50"
        ],
        "first": "al",
        "last": "et",
        "id": 83
    },
    "Z.W. Huang": {
        "listOfRef": [
            "51"
        ],
        "first": "Z",
        "middle": "W",
        "last": "Huang",
        "id": 84
    },
    "Tiggelen Van": {
        "listOfRef": [
            "51",
            "71",
            "72",
            "94",
            "119",
            "120"
        ],
        "first": "Tiggelen",
        "last": "Van",
        "id": 85
    },
    "K. Kailasanath": {
        "listOfRef": [
            "52"
        ],
        "first": "K",
        "last": "Kailasanath",
        "id": 86
    },
    "E.S. Oran": {
        "listOfRef": [
            "52"
        ],
        "first": "E",
        "middle": "S",
        "last": "Oran",
        "id": 87
    },
    "A. Sulmistras": {
        "listOfRef": [
            "54",
            "86"
        ],
        "first": "A",
        "last": "Sulmistras",
        "id": 88
    },
    "A. Teodorczyk": {
        "listOfRef": [
            "57"
        ],
        "first": "A",
        "last": "Teodorczyk",
        "id": 89
    },
    "S.M. Kogarko": {
        "listOfRef": [
            "58",
            "59",
            "60",
            "129"
        ],
        "first": "S",
        "middle": "M",
        "last": "Kogarko",
        "id": 90
    },
    "V.V. Adushkin": {
        "listOfRef": [
            "60"
        ],
        "first": "V",
        "middle": "V",
        "last": "Adushkin",
        "id": 91
    },
    "A.G. Lyamin": {
        "listOfRef": [
            "60"
        ],
        "first": "A",
        "middle": "G",
        "last": "Lyamin",
        "id": 92
    },
    "R.K. Kumar": {
        "listOfRef": [
            "61"
        ],
        "first": "R",
        "middle": "K",
        "last": "Kumar",
        "id": 93
    },
    "S. Laberge": {
        "listOfRef": [
            "62"
        ],
        "first": "S",
        "last": "Laberge",
        "id": 94
    },
    "K. Ramamurthi": {
        "listOfRef": [
            "63"
        ],
        "first": "K",
        "last": "Ramamurthi",
        "id": 95
    },
    "A. Freiman": {
        "listOfRef": [
            "66"
        ],
        "first": "A",
        "last": "Freiman",
        "id": 96
    },
    "B.H.K. Lee": {
        "listOfRef": [
            "67"
        ],
        "first": "B",
        "middle": "H.K",
        "last": "Lee",
        "id": 97
    },
    "H. Matsui": {
        "listOfRef": [
            "68",
            "80"
        ],
        "first": "H",
        "last": "Matsui",
        "id": 98
    },
    "R.I. Soloukhin": {
        "listOfRef": [
            "69"
        ],
        "first": "R",
        "middle": "I",
        "last": "Soloukhin",
        "id": 99
    },
    "A.K. Oppenheim": {
        "listOfRef": [
            "69"
        ],
        "first": "A",
        "middle": "K",
        "last": "Oppenheim",
        "id": 100
    },
    "M.H. Lefebvre": {
        "listOfRef": [
            "71"
        ],
        "first": "M",
        "middle": "H",
        "last": "Lefebvre",
        "id": 101
    },
    "E. Nzeyimana": {
        "listOfRef": [
            "71",
            "94"
        ],
        "first": "E",
        "last": "Nzeyimana",
        "id": 102
    },
    "J.C. Libouton": {
        "listOfRef": [
            "72"
        ],
        "first": "J",
        "middle": "C",
        "last": "Libouton",
        "id": 103
    },
    "M. Dormal": {
        "listOfRef": [
            "72"
        ],
        "first": "M",
        "last": "Dormal",
        "id": 104
    },
    "E.L. Litchfield": {
        "listOfRef": [
            "73"
        ],
        "first": "E",
        "middle": "L",
        "last": "Litchfield",
        "id": 105
    },
    "M.H. Hay": {
        "listOfRef": [
            "73"
        ],
        "first": "M",
        "middle": "H",
        "last": "Hay",
        "id": 106
    },
    "D.R. Forshey": {
        "listOfRef": [
            "73"
        ],
        "first": "D",
        "middle": "R",
        "last": "Forshey",
        "id": 107
    },
    "Y.K. Liu": {
        "listOfRef": [
            "74"
        ],
        "first": "Y",
        "middle": "K",
        "last": "Liu",
        "id": 108
    },
    "A. Macek": {
        "listOfRef": [
            "75"
        ],
        "first": "A",
        "last": "Macek",
        "id": 109
    },
    "V.I. Makeev": {
        "listOfRef": [
            "76"
        ],
        "first": "V",
        "middle": "I",
        "last": "Makeev",
        "id": 110
    },
    "Yu.A. Gostintsev": {
        "listOfRef": [
            "76"
        ],
        "first": "Yu",
        "middle": "A",
        "last": "Gostintsev",
        "id": 111
    },
    "V.V. Strogonov": {
        "listOfRef": [
            "76"
        ],
        "first": "V",
        "middle": "V",
        "last": "Strogonov",
        "id": 112
    },
    "Yu.A. Bokhon": {
        "listOfRef": [
            "76"
        ],
        "first": "Yu",
        "middle": "A",
        "last": "Bokhon",
        "id": 113
    },
    "Yu.N. Chernushkin": {
        "listOfRef": [
            "76"
        ],
        "first": "Yu",
        "middle": "N",
        "last": "Chernushkin",
        "id": 114
    },
    "V.N. Kulikov": {
        "listOfRef": [
            "76"
        ],
        "first": "V",
        "middle": "N",
        "last": "Kulikov",
        "id": 115
    },
    "A. Makris": {
        "listOfRef": [
            "77"
        ],
        "first": "A",
        "last": "Makris",
        "id": 116
    },
    "T.J. Oh": {
        "listOfRef": [
            "77"
        ],
        "first": "T",
        "middle": "J",
        "last": "Oh",
        "id": 117
    },
    "V.I. Manzhalei": {
        "listOfRef": [
            "78",
            "79"
        ],
        "first": "V",
        "middle": "I",
        "last": "Manzhalei",
        "id": 118
    },
    "V.V. Mitrofanov": {
        "listOfRef": [
            "78",
            "79",
            "81",
            "125"
        ],
        "first": "V",
        "middle": "V",
        "last": "Mitrofanov",
        "id": 119
    },
    "V.A. Subbotin": {
        "listOfRef": [
            "79"
        ],
        "first": "V",
        "middle": "A",
        "last": "Subbotin",
        "id": 120
    },
    "I.O. Moen": {
        "listOfRef": [
            "82",
            "83",
            "84",
            "85",
            "86",
            "87",
            "88",
            "104"
        ],
        "first": "I",
        "middle": "O",
        "last": "Moen",
        "id": 121
    },
    "M. Donato": {
        "listOfRef": [
            "83"
        ],
        "first": "M",
        "last": "Donato",
        "id": 122
    },
    "J.W. Funk": {
        "listOfRef": [
            "84"
        ],
        "first": "J",
        "middle": "W",
        "last": "Funk",
        "id": 123
    },
    "S.A. Ward": {
        "listOfRef": [
            "84",
            "87"
        ],
        "first": "S",
        "middle": "A",
        "last": "Ward",
        "id": 124
    },
    "G.M. Rude": {
        "listOfRef": [
            "84"
        ],
        "first": "G",
        "middle": "M",
        "last": "Rude",
        "id": 125
    },
    "P.A. Thibault": {
        "listOfRef": [
            "84",
            "86",
            "87",
            "104"
        ],
        "first": "P",
        "middle": "A",
        "last": "Thibault",
        "id": 126
    },
    "S.B. Murray": {
        "listOfRef": [
            "85",
            "88",
            "89",
            "90",
            "91",
            "104"
        ],
        "first": "S",
        "middle": "B",
        "last": "Murray",
        "id": 127
    },
    "D. Bjerketvedt": {
        "listOfRef": [
            "85",
            "86"
        ],
        "first": "D",
        "last": "Bjerketvedt",
        "id": 128
    },
    "A. Rinnan": {
        "listOfRef": [
            "85",
            "102"
        ],
        "first": "A",
        "last": "Rinnan",
        "id": 129
    },
    "G. Thomas": {
        "listOfRef": [
            "86"
        ],
        "first": "G",
        "last": "Thomas",
        "id": 130
    },
    "T. Dean": {
        "listOfRef": [
            "87"
        ],
        "first": "T",
        "last": "Dean",
        "id": 131
    },
    "J.J. Gottlieb": {
        "listOfRef": [
            "88"
        ],
        "first": "J",
        "middle": "J",
        "last": "Gottlieb",
        "id": 132
    },
    "C. Coffey": {
        "listOfRef": [
            "88"
        ],
        "first": "C",
        "last": "Coffey",
        "id": 133
    },
    "D. Remboutsikas": {
        "listOfRef": [
            "88"
        ],
        "first": "D",
        "last": "Remboutsikas",
        "id": 134
    },
    "M. Sichel": {
        "listOfRef": [
            "92",
            "128"
        ],
        "first": "M",
        "last": "Sichel",
        "id": 135
    },
    "Z. Gabrijel": {
        "listOfRef": [
            "92"
        ],
        "first": "Z",
        "last": "Gabrijel",
        "id": 136
    },
    "R.D. Oza": {
        "listOfRef": [
            "92"
        ],
        "first": "R",
        "middle": "D",
        "last": "Oza",
        "id": 137
    },
    "R. Vandermolen": {
        "listOfRef": [
            "92"
        ],
        "first": "R",
        "last": "Vandermolen",
        "id": 138
    },
    "M.E. Nolan": {
        "listOfRef": [
            "93"
        ],
        "first": "M",
        "middle": "E",
        "last": "Nolan",
        "id": 139
    },
    "S. Ohyagi": {
        "listOfRef": [
            "95"
        ],
        "first": "S",
        "last": "Ohyagi",
        "id": 140
    },
    "T. Yoshihashi": {
        "listOfRef": [
            "95"
        ],
        "first": "T",
        "last": "Yoshihashi",
        "id": 141
    },
    "Y. Harigaya": {
        "listOfRef": [
            "95"
        ],
        "first": "Y",
        "last": "Harigaya",
        "id": 142
    },
    "M.D. Pedley": {
        "listOfRef": [
            "97"
        ],
        "first": "M",
        "middle": "D",
        "last": "Pedley",
        "id": 143
    },
    "C.A. Bennett": {
        "listOfRef": [
            "97"
        ],
        "first": "C",
        "middle": "A",
        "last": "Bennett",
        "id": 144
    },
    "D.L. Fenton": {
        "listOfRef": [
            "97"
        ],
        "first": "D",
        "middle": "L",
        "last": "Fenton",
        "id": 145
    },
    "O. Peraldi": {
        "listOfRef": [
            "97"
        ],
        "first": "O",
        "last": "Peraldi",
        "id": 146
    },
    "U. Pfahl": {
        "listOfRef": [
            "98"
        ],
        "first": "U",
        "last": "Pfahl",
        "id": 147
    },
    "M. Plaster": {
        "listOfRef": [
            "99"
        ],
        "first": "M",
        "last": "Plaster",
        "id": 148
    },
    "D.W. Stamps": {
        "listOfRef": [
            "105",
            "106",
            "114"
        ],
        "first": "D",
        "middle": "W",
        "last": "Stamps",
        "id": 149
    },
    "S.R. Tieszen": {
        "listOfRef": [
            "105",
            "106",
            "112",
            "113",
            "114"
        ],
        "first": "S",
        "middle": "R",
        "last": "Tieszen",
        "id": 150
    },
    "R.A. Strehlow": {
        "listOfRef": [
            "107",
            "108",
            "109",
            "110",
            "111"
        ],
        "first": "R",
        "middle": "A",
        "last": "Strehlow",
        "id": 151
    },
    "R. Liangminas": {
        "listOfRef": [
            "110"
        ],
        "first": "R",
        "last": "Liangminas",
        "id": 152
    },
    "R.H. Watson": {
        "listOfRef": [
            "110"
        ],
        "first": "R",
        "middle": "H",
        "last": "Watson",
        "id": 153
    },
    "J.R. Eyman": {
        "listOfRef": [
            "110"
        ],
        "first": "J",
        "middle": "R",
        "last": "Eyman",
        "id": 154
    },
    "R.E. Maurer": {
        "listOfRef": [
            "111"
        ],
        "first": "R",
        "middle": "E",
        "last": "Maurer",
        "id": 155
    },
    "S. Rajan": {
        "listOfRef": [
            "111"
        ],
        "first": "S",
        "last": "Rajan",
        "id": 156
    },
    "M.P. Sherman": {
        "listOfRef": [
            "112",
            "113"
        ],
        "first": "M",
        "middle": "P",
        "last": "Sherman",
        "id": 157
    },
    "S. Tsuge": {
        "listOfRef": [
            "115"
        ],
        "first": "S",
        "last": "Tsuge",
        "id": 158
    },
    "H. Furukawa": {
        "listOfRef": [
            "115"
        ],
        "first": "H",
        "last": "Furukawa",
        "id": 159
    },
    "M. Matsukawa": {
        "listOfRef": [
            "115"
        ],
        "first": "M",
        "last": "Matsukawa",
        "id": 160
    },
    "T. Nakagawa": {
        "listOfRef": [
            "115"
        ],
        "first": "T",
        "last": "Nakagawa",
        "id": 161
    },
    "P.A. Urtiew": {
        "listOfRef": [
            "117",
            "126",
            "127"
        ],
        "first": "P",
        "middle": "A",
        "last": "Urtiew",
        "id": 162
    },
    "C.M. Tarver": {
        "listOfRef": [
            "117"
        ],
        "first": "C",
        "middle": "M",
        "last": "Tarver",
        "id": 163
    },
    "Molen Vander": {
        "listOfRef": [
            "118"
        ],
        "first": "Molen",
        "last": "Vander",
        "id": 164
    },
    "M. Vandermeiren": {
        "listOfRef": [
            "119",
            "120"
        ],
        "first": "M",
        "last": "Vandermeiren",
        "id": 165
    },
    "A.A. Vasil'ev": {
        "listOfRef": [
            "121",
            "122",
            "123",
            "124"
        ],
        "first": "A",
        "middle": "A",
        "last": "Vasil'ev",
        "id": 166
    },
    "V.V. Grigor'ev": {
        "listOfRef": [
            "123"
        ],
        "first": "V",
        "middle": "V",
        "last": "Grigor'ev",
        "id": 167
    },
    "Yu.A. Nikolaev": {
        "listOfRef": [
            "124"
        ],
        "first": "Yu",
        "middle": "A",
        "last": "Nikolaev",
        "id": 168
    },
    "Ul'yanitskii": {
        "listOfRef": [
            "124"
        ],
        "last": "Ul'yanitskii",
        "id": 169
    },
    "B.V. Voitsekhovskii": {
        "listOfRef": [
            "125"
        ],
        "first": "B",
        "middle": "V",
        "last": "Voitsekhovskii",
        "id": 170
    },
    "M.E. Topchian": {
        "listOfRef": [
            "125"
        ],
        "first": "M",
        "middle": "E",
        "last": "Topchian",
        "id": 171
    },
    "P. Wolanski": {
        "listOfRef": [
            "128"
        ],
        "first": "P",
        "last": "Wolanski",
        "id": 172
    },
    "C.W. Kauffman": {
        "listOfRef": [
            "128"
        ],
        "first": "C",
        "middle": "W",
        "last": "Kauffman",
        "id": 173
    },
    "Ia.B. Zeldovich": {
        "listOfRef": [
            "129"
        ],
        "first": "Ia",
        "middle": "B",
        "last": "Zeldovich",
        "id": 174
    },
    "N.N. Simonov": {
        "listOfRef": [
            "129"
        ],
        "first": "N",
        "middle": "N",
        "last": "Simonov",
        "id": 175
    },
    "R. Zitoun": {
        "listOfRef": [
            "130"
        ],
        "first": "R",
        "last": "Zitoun",
        "id": 176
    },
    "B. Deshaies": {
        "listOfRef": [
            "130"
        ],
        "first": "B",
        "last": "Deshaies",
        "id": 177
    }
}